{
  "queue": [
    {
      "pattern_name": "構造J_全12星座1行メッセージ型（4/12）",
      "category": "全星座・日次運勢",
      "content": "🔮 4/12の12星座\n\n牡羊座　動いた分だけ、返ってくる。\n牡牛座　焦らず待つのが、今日の正解。\n双子座　気になるあの人、実は意識してる。\n蟹　　座　感じた気持ちは、全部正解。\n獅子座　チャンスは、静かに来る。\n乙女座　気遣いが、ちゃんと伝わってる。\n天秤座　誰かの一言が、転換点になる。\n蠍　　座　深読みより、素直に動こう。\n射手座　踏み出した一歩が、景色を変える。\n山羊座　地道な積み重ねが、今日花開く。\n水瓶座　個性を出すほど、縁が生まれる。\n魚　　座　直感は、今日に限り信じていい。\n\nあなたの星座はどうでしたか？🌙\n\n#星座占い",
      "hashtag": "#星座占い",
      "time_slot": "午前（10〜12時台）",
      "scheduled_hour": 10,
      "id": "post_20260412_0846_J_001",
      "platform": "threads",
      "is_affiliate": false,
      "affiliate_comment": null,
      "status": "queued",
      "quality_warnings": []
    },
    {
      "pattern_name": "構造G_注意喚起+限定型②（今週急変する・朝向け）",
      "category": "星座運勢",
      "content": "今週、ガラッと変わる星座。\n\nたった3つだけです。\n\n牡羊座、獅子座、射手座\n\n牡羊座さんは、思いがけない嬉しい提案が舞い込みます。迷わず前に進んでください。\n\n獅子座さんは、人間関係が良い方向に動きます。新しい繋がりが開かれるでしょう。\n\n射手座さんは、好機が来ます。今週中の決断がカギになります。\n\nあなたの星座は入ってましたか？コメントで教えてください🔮\n\n#今週の占い",
      "hashtag": "#今週の占い",
      "time_slot": "朝（6〜9時台）",
      "scheduled_hour": 9,
      "id": "post_20260411_2047_exp_002",
      "platform": "threads",
      "is_affiliate": false,
      "affiliate_comment": null,
      "status": "queued",
      "quality_warnings": [
        "行4が長すぎ: 39文字「牡羊座さんは、思いがけない嬉しい提案が舞...」（最大25文字）[threads]"
      ]
    },
    {
      "pattern_name": "構造G_注意喚起+限定型③（今月・今週後半急上昇）",
      "category": "運気変動",
      "content": "今月、急上昇する星座。\n\nたった3つだけです。\n\n牡羊座、獅子座、射手座\n\n牡羊座さんは、この週末から新しい話題が舞い込みます。思わぬ好機が来ます。\n\n獅子座さんは、人間関係が急に広がる時期。嬉しい出会いが増えていきます。\n\n射手座さんは、仕事や創作で認められやすくなります。これまでの努力が花開くタイミングです。\n\n🍀を置いた方に、今週中に嬉しい連絡が届きます。\n\n#今月の占い",
      "hashtag": "#今月の占い",
      "time_slot": "午前（10〜12時台）",
      "scheduled_hour": 10,
      "id": "post_20260411_2047_exp_003",
      "platform": "threads",
      "is_affiliate": false,
      "affiliate_comment": null,
      "status": "queued",
      "quality_warnings": [
        "行4が長すぎ: 36文字「牡羊座さんは、この週末から新しい話題が舞...」（最大25文字）[threads]"
      ]
    },
    {
      "pattern_name": "構造G_注意喚起+限定型④（今日・今週大きく動く）",
      "category": "運勢・変化",
      "content": "今週、ガラッと変わる星座。\n\nたった3つだけです。\n\n牡羊座、獅子座、射手座\n\n牡羊座さんは、仕事で思わぬ好機が。動きが早い方ほど、嬉しい展開が待ってます。\n\n獅子座さんは、人間関係が大きく動く時期。新しい繋がりが、今週中に広がります。\n\n射手座さんは、金運が急上昇。予想外の嬉しい知らせが舞い込みやすい週です。\n\n🍀を置いた方に、今週中に嬉しい連絡が届きます。\n\n#今週の占い",
      "hashtag": "#今週の占い",
      "time_slot": "午後（12〜15時台）",
      "scheduled_hour": 12,
      "id": "post_20260411_2047_exp_004",
      "platform": "threads",
      "is_affiliate": false,
      "affiliate_comment": null,
      "status": "queued",
      "quality_warnings": [
        "行4が長すぎ: 38文字「牡羊座さんは、仕事で思わぬ好機が。動きが...」（最大25文字）[threads]"
      ]
    },
    {
      "pattern_name": "構造G_注意喚起+限定型⑤（今週後半ガラッと変わる）",
      "category": "星座運勢",
      "content": "今週後半、ガラッと変わる星座。\nたった3つだけです。\n\n牡羊座、獅子座、射手座\n\n牡羊座さんは、思いがけない好機が舞い込みます。迷わず動いてください。\n\n獅子座さんは、人間関係が急展開。嬉しい再会や新しいご縁が生まれやすい時期です。\n\n射手座さんは、仕事運が急上昇。今までの頑張りが評価される瞬間が来ます。\n\n🍀を置いた方に、今週中に嬉しい連絡が届きます。\n\n#今週の占い",
      "hashtag": "#今週の占い",
      "time_slot": "午後（13〜15時台）",
      "scheduled_hour": 15,
      "character_count": 198,
      "hook_length": 13,
      "engagement_prediction": "高（フック実績v=1514参照、限定型+ポジティブ変化で推定eng率16-18%）",
      "id": "post_20260411_2047_exp_005",
      "platform": "threads",
      "is_affiliate": false,
      "affiliate_comment": null,
      "status": "queued",
      "quality_warnings": [
        "行4が長すぎ: 34文字「牡羊座さんは、思いがけない好機が舞い込み...」（最大25文字）[threads]"
      ]
    },
    {
      "pattern_name": "構造F_告白・暴露型①（占い師として正直に言います）",
      "category": "週間運勢",
      "content": "正直に言います。\n\n今週後半、牡羊座と獅子座は\n『やりすぎ』の傾向が出ています。\n\n勢いで決断したり、\n相手の話を聞かずに進めたり。\n火星の影響が強いんです。\n\n占い師として見ると、\nそこが今週のリスク。\n\n一度立ち止まって、\n相手の意見を聞く時間を\n作ってみてください。\n\n運気は『確認』で整います。\n🔮",
      "hashtag": "#今週の占い",
      "time_slot": "夜（19〜21時台）",
      "scheduled_hour": 19,
      "id": "post_20260411_2047_exp_006",
      "platform": "threads",
      "is_affiliate": false,
      "affiliate_comment": null,
      "status": "queued",
      "quality_warnings": [
        "縦長すぎ: 18行（最大16行）[threads]",
        "ハッシュタグが含まれていない[threads]"
      ]
    },
    {
      "pattern_name": "構造F_告白・暴露型②（実は〜という真実を伝えます）",
      "category": "星座運勢・人間関係",
      "content": "実は、今夜の月が教えてくれることがあります。\n\n4月中旬に向けて、あなたが「我慢していた本音」を言うチャンスが来ています。獅子座・射手座・牡羊座の皆さんは特に。\n\n占い師としての本音ですが、言わないままでいると6月までそのモヤモヤを引きずります。\n\nだからこそ今週中に、信頼できる人には「本当の気持ち」を伝えてください。木星がその勇気を後押ししていますよ。\n\nあなたは今夜、誰かに何か言いたいことありませんか？🔮",
      "hashtag": "#今週の占い",
      "time_slot": "夜（19〜21時台）",
      "scheduled_hour": 21,
      "id": "post_20260411_2047_exp_007",
      "platform": "threads",
      "is_affiliate": false,
      "affiliate_comment": null,
      "status": "queued",
      "quality_warnings": [
        "行2が長すぎ: 56文字「4月中旬に向けて、あなたが「我慢していた...」（最大25文字）[threads]",
        "ハッシュタグが含まれていない[threads]"
      ]
    }
  ]
}