{
  "queue": [
    {
      "pattern_name": "構造H_しいたけ式共感・場面描写型（恋愛の悩みの場面を具体的に描写・恋愛迷子ターゲット・通勤ピーク）",
      "category": "占い師の視点・哲学",
      "content": "恋愛は、占いで解決しない。\n\n通勤電車の中で「彼からのLINEがこない」と悩む。占い師として答えを出せることもある。でも本当に必要なのは、その先の「どう動くか」なんです。\n\n占いは羅針盤であって、目的地ではない。\n\nあなたが決めた選択が、運命を変えていく。星はそれを応援しているだけです。\n\nあなたにとって、決断の基準は何ですか？",
      "hashtag": "#星座占い",
      "time_slot": "しいたけ共感型（08:07）",
      "scheduled_hour": 8,
      "scheduled_minute": 7,
      "id": "post_20260414_0252_exp_003",
      "platform": "threads",
      "is_affiliate": false,
      "affiliate_comment": null,
      "status": "queued",
      "quality_warnings": [
        "行2が長すぎ: 70文字「通勤電車の中で「彼からのLINEがこない...」（最大25文字）[threads]",
        "ハッシュタグが含まれていない[threads]"
      ]
    },
    {
      "pattern_name": "構造G_天体根拠×仕事アドバイス型（今日の仕事運・仕事迷子ターゲット・仕事開始後のひと息）",
      "category": "仕事運",
      "content": "4/14、仕事が動く星座。\nたった3つだけです。\n\n牡羊座、獅子座、射手座\n\n牡羊座さんは、朝のメール返信で思わぬ新しい案件が舞い込みます。積極的に進めて大丈夫。\n\n獅子座さんは、今日中に上司からのちょっと嬉しい声がかかる予感。自分の成果をそっと示しておくといいですよ。\n\n射手座さんは、昼過ぎの打ち合わせで視点が変わります。その違和感を大事にしてください。\n\nあなたの星座は入ってましたか？コメントで教えてください🔮\n\n#今日の運勢",
      "hashtag": "#今日の運勢",
      "time_slot": "仕事アドバイス型（09:37）",
      "scheduled_hour": 9,
      "scheduled_minute": 37,
      "id": "post_20260414_0252_exp_004",
      "platform": "threads",
      "is_affiliate": false,
      "affiliate_comment": null,
      "status": "queued",
      "quality_warnings": [
        "行4が長すぎ: 42文字「牡羊座さんは、朝のメール返信で思わぬ新し...」（最大25文字）[threads]"
      ]
    },
    {
      "pattern_name": "構造F_スピ×ラッキーアイテム型（ラッキーカラー・ラッキーアイテム・軽くて楽しい・スピ好きターゲット・昼休み）",
      "category": "ラッキーアイテム×昼休み運",
      "content": "昼休みに持ち歩くといいもの。\n\n今日、白いハンカチを\nポケットに忍ばせておくと\n午後からの運気が変わります。\n\nラッキーカラーは白×薄紫。\nこの2色を視界に入れるだけで\n直感が冴えやすくなる日。\n\nお昼ご飯のときに\n白いお皿を選んでみてください🍽️\n小さなことが\n大きな流れを変えますよ。\n\nあなたは今日、\n何色を身につけていますか？\nコメントで教えてください🔮",
      "hashtag": "#今日の運勢",
      "time_slot": "スピ×ラッキー型（12:07）",
      "scheduled_hour": 12,
      "scheduled_minute": 7,
      "id": "post_20260414_0252_exp_005",
      "platform": "threads",
      "is_affiliate": false,
      "affiliate_comment": null,
      "status": "queued",
      "quality_warnings": [
        "縦長すぎ: 18行（最大16行）[threads]",
        "ハッシュタグが含まれていない[threads]"
      ]
    },
    {
      "pattern_name": "構造H_しいたけ式深掘り哲学型（占い師の視点・深い言葉・内省モード・仕事迷子＋スピ好きターゲット・退勤後）",
      "category": "占い師の内省・哲学",
      "content": "占いが当たる理由って、\n未来を言い当てるからじゃなくて、\nあなたが「その言葉を聞いて動く」からだと思うんです。\n\n仕事で迷ったとき、占いは選択肢そのものじゃなくて、\n心が決めた答えを「確認させてくれる鏡」かもしれない。\n\nだから外れた占いも、\n実はあなたが違う道を選んだ証拠なのかも。\n\nあなたは占いを信じていますか？\nそれとも、自分を信じるための道具として使っていますか？\n\n#星座占い",
      "hashtag": "#星座占い",
      "time_slot": "哲学深掘り型（18:07）",
      "scheduled_hour": 18,
      "scheduled_minute": 7,
      "id": "post_20260414_0252_exp_006",
      "platform": "threads",
      "is_affiliate": false,
      "affiliate_comment": null,
      "status": "queued",
      "quality_warnings": [
        "行3が長すぎ: 26文字「あなたが「その言葉を聞いて動く」からだと...」（最大25文字）[threads]"
      ]
    }
  ]
}